readdat/__init__.py
readdat/read.py
readdat/version.py
readdat/write.py
readdat/arb/Arbitrary_Waveform_Generator.py
readdat/arb/__init__.py
readdat/arb/read_arb.py
readdat/beb0/__init__.py
readdat/beb0/beb0.py
readdat/bin_iris/__init__.py
readdat/bin_iris/bin_iris.py
readdat/database/__init__.py
readdat/database/codatabase.py
readdat/dzt/__init__.py
readdat/dzt/dzt_file.py
readdat/dzt/read_dzt.py
readdat/h5/__init__.py
readdat/h5/create_h5.py
readdat/mat/__init__.py
readdat/mat/read_mat.py
readdat/mat/read_mat_quantum.py
readdat/mat/read_mat_ultrasonic_scan.py
readdat/mseed/__init__.py
readdat/seg2/__init__.py
readdat/seg2/hiwai_conversion_script.py
readdat/seg2/plot_temperature_humidity_from_seg2coda.py
readdat/seg2/read_seg2.py
readdat/seg2/read_seg2cdz.py
readdat/seg2/read_seg2coda.py
readdat/seg2/read_seg2default.py
readdat/seg2/read_seg2musc.py
readdat/seg2/read_seg2must.py
readdat/seg2/read_seg2ondulys.py
readdat/seg2/read_seg2tomag.py
readdat/seg2/seg2_to_su.py
readdat/seg2/seg2musc_to_segymusc.py
readdat/seg2/seg2musc_to_sumusc.py
readdat/seg2/show_seg2.py
readdat/segd/__init__.py
readdat/segd/read_segd2X.py
readdat/segd/read_segd30.py
readdat/segd/read_segd_for_su.py
readdat/segy/__init__.py
readdat/segy/createsegy.py
readdat/segy/read_segy.py
readdat/segy/read_segymusc.py
readdat/segy/write_obspymusc_as_segymusc.py
readdat/sig/__init__.py
readdat/sig/read_sig.py
readdat/su/__init__.py
readdat/su/read_su.py
readdat/su/read_sumusc.py
readdat/su/write_obspymusc_as_sumusc.py
readdat/test/__init__.py
readdat/test/test_bin_iris.py
readdat/test/test_create_h5_model.py
readdat/test/test_database.py
readdat/test/test_datetime_conversion.py
readdat/test/test_filesamples.py
readdat/test/test_matquantum.py
readdat/test/test_mseed.py
readdat/test/test_pytest.py
readdat/test/test_seg2.py
readdat/test/test_seg2musc_to_segymusc.py
readdat/test/test_seg2musc_to_sumusc.py
readdat/test/test_segd.py
readdat/test/test_sig.py
readdat/test/test_tusmus.py
readdat-2.6.21.dist-info/licenses/LICENSE
readdat-2.6.21.dist-info/METADATA
readdat-2.6.21.dist-info/WHEEL
readdat-2.6.21.dist-info/top_level.txt
readdat-2.6.21.dist-info/RECORD
