Metadata-Version: 2.4
Name: readdat
Version: 2.6.21
Author: Maximilien Lehujeur, Thibaud Devie, Pierric Mora, Olivier Durand, Apolline Laurent, Rouba Hariri, and the GeoEND Team
Author-email: maximilien.lehujeur@univ-eiffel.fr
Classifier: Programming Language :: Python :: 3
Classifier: Operating System :: POSIX :: Linux
Classifier: Operating System :: Microsoft :: Windows
Requires-Python: >=3.8,<3.13
License-File: LICENSE
Requires-Dist: numpy
Requires-Dist: matplotlib
Requires-Dist: obspy
Requires-Dist: pytest
Requires-Dist: parse
Requires-Dist: jupyter
Requires-Dist: notebook
Requires-Dist: pytz
Requires-Dist: pandas
Requires-Dist: pyseg2>=1.4.5
Requires-Dist: dbpack>=1.0.0
Requires-Dist: seiscod>=3.3.4
Requires-Dist: tqdm
Dynamic: author
Dynamic: author-email
Dynamic: classifier
Dynamic: description
Dynamic: description-content-type
Dynamic: license-file
Dynamic: requires-dist
Dynamic: requires-python
